eric_redis_queues/__init__.py
eric_redis_queues/repository.py
eric_redis_queues-2.0.0.10.dist-info/LICENSE
eric_redis_queues-2.0.0.10.dist-info/METADATA
eric_redis_queues-2.0.0.10.dist-info/WHEEL
eric_redis_queues-2.0.0.10.dist-info/RECORD
