Metadata-Version: 2.3
Name: eric-redis-queues
Version: 2.0.0.10
Summary: Redis support for eric-sse
License: MIT
Keywords: sse,server sent events,queue,concurrency
Author: Luca Stretti
Author-email: laxertu@gmail.com
Requires-Python: >=3.10, <3.12
Classifier: License :: OSI Approved :: MIT License
Classifier: Programming Language :: Python :: 3
Classifier: Programming Language :: Python :: 3.10
Classifier: Programming Language :: Python :: 3.11
Requires-Dist: asyncio (>=3.4.3,<3.4.4)
Requires-Dist: eric-sse (==2.1.1.2)
Requires-Dist: redis (==6.2.0)
Project-URL: Homepage, https://laxertu.github.io/eric-redis-queues
Project-URL: Issues, https://github.com/laxertu/eric/issues
Project-URL: Repository, https://github.com/laxertu/eric-redis-queues
